scipystats/__init__.py
scipystats/main.py
scipystats-0.0.1.dist-info/METADATA
scipystats-0.0.1.dist-info/WHEEL
scipystats-0.0.1.dist-info/licenses/LICENSE
scipystats-0.0.1.dist-info/RECORD
