Metadata-Version: 2.3
Name: scipystats
Version: 0.0.1
Summary: This library is not that useful. Perhaps someday it will become great.
Author-email: Matvey Makeenkov <matmak@list.ru>
License-File: LICENSE
Classifier: License :: OSI Approved :: MIT License
Classifier: Operating System :: OS Independent
Classifier: Programming Language :: Python :: 3
Requires-Python: >=3.10.0
